{
  "config": {
    "contents": {
      "data": {
        "batch_size": 16
      },
      "device": "cpu",
      "experiment": "smoke",
      "model": {
        "hidden_dim": 64,
        "in_dim": 32,
        "out_dim": 4
      },
      "optimizer": {
        "lr": 0.0,
        "name": "noop"
      },
      "seed": 1234,
      "train": {
        "steps": 10
      }
    },
    "path": "configs/smoke.yaml",
    "sha256": "91e87d4118b9fbcf52cf033e1361b8daa0d2e508183b9da251a68c0ce8cf9d20"
  },
  "cost_usd": null,
  "experiment": "smoke",
  "finished_at": "2026-07-18T18:33:17.877705+00:00",
  "git_dirty": true,
  "git_sha": "d777d2242c097ae4afe144e73d53baec6cc54394",
  "gpu_type": "cpu",
  "metrics": {
    "loss_first": 1.4361190795898438,
    "loss_last": 1.3642306327819824,
    "losses": [
      1.4361190795898438,
      1.3620903491973877,
      1.3685613870620728,
      1.4540300369262695,
      1.3413643836975098,
      1.3630521297454834,
      1.5337377786636353,
      1.422964334487915,
      1.340366005897522,
      1.3642306327819824
    ],
    "max_param_delta": 0.0,
    "optimizer": "noop",
    "steps": 10
  },
  "schema_version": 1,
  "seed": 1234,
  "started_at": "2026-07-18T18:33:16.288193+00:00",
  "wall_time_s": 1.5890026669949293
}
